LICENSE.txt
MANIFEST.in
README.rst
setup.py
bin/ufo2otf
ufo2otf/__init__.py
ufo2otf/argparse.py
ufo2otf/compilers.py
ufo2otf/diagnostics.py
ufo2otf.egg-info/PKG-INFO
ufo2otf.egg-info/SOURCES.txt
ufo2otf.egg-info/dependency_links.txt
ufo2otf.egg-info/top_level.txt