Metadata-Version: 1.1
Name: ufo2otf
Version: 0.2.2
Summary: Take UFO font sources and generate OTF’s and webfonts
Home-page: http://packages.python.org/an_example_pypi_project
Author: Eric Schrijver
Author-email: eric@ericschrijver.nl
License: BSD
Keywords: font utility web ufo otf conversion command line
Platform: UNKNOWN
Classifier: Environment :: Console
Classifier: Development Status :: 3 - Alpha
Classifier: Topic :: Multimedia :: Graphics
Classifier: Topic :: Multimedia :: Graphics :: Graphics Conversion
Classifier: Topic :: Utilities
Classifier: License :: OSI Approved :: BSD License
